labanotation/__init__.py
labanotation/algorithm.py
labanotation/cluster.py
labanotation/filter.py
labanotation/io.py
labanotation/joint_constants.py
labanotation/k4a_kinematics.py
labanotation/kinematics.py
labanotation/laban_class.py
labanotation/labanotation_utils.py
labanotation/math_utils.py
labanotation/pose_utils.py
labanotation/process.py
labanotation/apps/__init__.py
labanotation/apps/csv_to_labanotation.py
labanotation/data/__init__.py
labanotation/data/laban_suite_data.py
labanotation/visualization/__init__.py
labanotation/visualization/laban_to_image.py
tests/__init__.py
tests/test_labanotation_utils.py
tests/test_proces.py
tests/visualization_tests/__init__.py
tests/visualization_tests/test_laban_to_image.py
labanotation-0.1.4.dist-info/LICENSE
labanotation-0.1.4.dist-info/METADATA
labanotation-0.1.4.dist-info/WHEEL
labanotation-0.1.4.dist-info/entry_points.txt
labanotation-0.1.4.dist-info/top_level.txt
labanotation-0.1.4.dist-info/RECORD
