Metadata-Version: 2.1
Name: labanotation
Version: 0.1.4
Summary: Labanotation tool library
Home-page: https://github.com/iory/labanotation
Author: iory
Author-email: ab.ioryz@gmail.com
License: MIT
Platform: UNKNOWN
Classifier: Development Status :: 5 - Production/Stable
Classifier: Intended Audience :: Developers
Classifier: Natural Language :: English
Classifier: License :: OSI Approved :: MIT License
Classifier: Programming Language :: Python
Classifier: Programming Language :: Python :: 3.5
Classifier: Programming Language :: Python :: 3.6
Classifier: Programming Language :: Python :: 3.7
Classifier: Programming Language :: Python :: Implementation :: CPython
License-File: LICENSE
Requires-Dist: extendedos
Requires-Dist: numpy
Requires-Dist: opencv-python
Requires-Dist: pandas
Requires-Dist: pybsc[all]
Requires-Dist: scikit-robot
Requires-Dist: scipy
